data/with_actions.h5
eagerx_examples/__init__.py
eagerx_examples/classifier.py
eagerx_examples/example_classifier.py
eagerx_examples/example_full_state.py
eagerx_examples/example_pid_only.py
eagerx_examples/pid.py
eagerx_examples-0.1.5.dist-info/LICENSE
eagerx_examples-0.1.5.dist-info/WHEEL
eagerx_examples-0.1.5.dist-info/METADATA
eagerx_examples-0.1.5.dist-info/RECORD
