Metadata-Version: 2.1
Name: eagerx-examples
Version: 0.1.5
Summary: Code examples of EAGERx.
Home-page: https://github.com/eager-dev/eagerx_examples
License: Apache2.0
Author: Bas van der Heijden
Author-email: d.s.vanderheijden@tudelft.nl
Requires-Python: >=3.6.2,<4.0.0
Classifier: License :: Other/Proprietary License
Classifier: Programming Language :: Python :: 3
Classifier: Programming Language :: Python :: 3.10
Classifier: Programming Language :: Python :: 3.7
Classifier: Programming Language :: Python :: 3.8
Classifier: Programming Language :: Python :: 3.9
Requires-Dist: eagerx (>=0.1.10,<0.2.0)
Requires-Dist: h5py (>=2.9.0,<3.0.0)
Requires-Dist: pyglet (>=1.5.21,<2.0.0)
Requires-Dist: stable-baselines3 (==1.1.0)
Project-URL: Documentation, https://eagerx.readthedocs.io/en/master/
Project-URL: Repository, https://github.com/eager-dev/eagerx_examples
